<?xml version="1.0" encoding="utf-8"?>
<odoo>
    <record id="ir_cron_view_tree_inherit_running" model="ir.ui.view">
        <field name="name">ir.cron.view.tree.inherit.running</field>
        <field name="model">ir.cron</field>
        <field name="inherit_id" ref="base.ir_cron_view_tree"/>
        <field name="arch" type="xml">
            <xpath expr="//tree" position="inside">
                <field name="is_running" string="Running"/>
            </xpath>
        </field>
    </record>
</odoo>
